setup.py
cutools/__init__.py
cutools.egg-info/PKG-INFO
cutools.egg-info/SOURCES.txt
cutools.egg-info/dependency_links.txt
cutools.egg-info/entry_points.txt
cutools.egg-info/requires.txt
cutools.egg-info/top_level.txt
cutools/cli/__init__.py
cutools/cli/cugit.py
cutools/diff/__init__.py
cutools/vcs/__init__.py
cutools/vcs/git.py