Metadata-Version: 1.1
Name: cutools
Version: 0.3.3
Summary: Check local modifications in upstream branch
Home-page: https://github.com/ecarreras/cutools
Author: Eduard Carreras
Author-email: ecarreras@gmail.com
License: Copyright (c) 2012, Eduard Carreras <ecarreras@gmail.com>
